cryptopyutils/__init__.py
cryptopyutils/cert.py
cryptopyutils/config.py
cryptopyutils/csr.py
cryptopyutils/dirs.py
cryptopyutils/files.py
cryptopyutils/password.py
cryptopyutils/privatekey.py
cryptopyutils/publickey.py
cryptopyutils/sshkeypair.py
cryptopyutils/utils.py
cryptopyutils/cli/__init__.py
cryptopyutils/cli/askpgen.py
cryptopyutils/cli/certconfig.yaml
cryptopyutils/cli/cli.rst
cryptopyutils/cli/consttimecomp.py
cryptopyutils/cli/csrgen.py
cryptopyutils/cli/dirs.py
cryptopyutils/cli/pwdenc.py
cryptopyutils/cli/pwdverif.py
cryptopyutils/cli/selfsignedgen.py
cryptopyutils/cli/sshkeypairgen.py
cryptopyutils/others/__init__.py
cryptopyutils/others/asymsignverify.py
cryptopyutils/others/examples.rst
cryptopyutils/others/files.py
cryptopyutils/others/rsaencdec.py
cryptopyutils-0.1.0.dist-info/METADATA
cryptopyutils-0.1.0.dist-info/NOTICE
cryptopyutils-0.1.0.dist-info/WHEEL
cryptopyutils-0.1.0.dist-info/top_level.txt
cryptopyutils-0.1.0.dist-info/RECORD
