Metadata-Version: 2.1
Name: cryptopyutils
Version: 0.1.0
Summary: High-level Python3 cryptography library using `cryptography` with sensible defaults and CLI scripts.
Home-page: https://github.com/dheurtev/cryptopyutils
Author: David HEURTEVENT
Author-email: david@heurtevent.org
License: Apache License 2.0
Project-URL: Documentation, https://cryptopyutils.readthedocs.io/
Project-URL: Source, https://github.com/dheurtev/cryptopyutils
Project-URL: Changelog, https://github.com/dheurtev/cryptopyutils/blob/main/CHANGELOG.rst
Project-URL: Tracker, https://github.com/dheurtev/cryptopyutils/issues
Platform: any
Classifier: Programming Language :: Python
Classifier: Programming Language :: Python :: 3
Classifier: Programming Language :: Python :: 3 :: Only
Classifier: Development Status :: 5 - Production/Stable
Classifier: License :: OSI Approved :: Apache Software License
Classifier: Intended Audience :: Developers
Classifier: Topic :: Security
Classifier: Topic :: Security :: Cryptography
Classifier: Topic :: Software Development :: Libraries
Classifier: Topic :: Software Development :: Libraries :: Python Modules
Classifier: Topic :: Utilities
Classifier: Operating System :: POSIX :: Linux
Requires-Python: >=3.8
License-File: NOTICE
Requires-Dist: pyscaffold (<5.0,>=4.2)
Requires-Dist: cryptography (>=2.5)
Requires-Dist: distro
Requires-Dist: pyyaml
Requires-Dist: myst-parser[linkify]
Requires-Dist: sphinx-rtd-theme
Requires-Dist: importlib-metadata ; python_version < "3.8"
Provides-Extra: lint
Requires-Dist: black ; extra == 'lint'
Requires-Dist: isort ; extra == 'lint'
Requires-Dist: flake8 ; extra == 'lint'
Requires-Dist: flake8-black ; extra == 'lint'
Requires-Dist: flake8-isort ; extra == 'lint'
Requires-Dist: flake8-commas ; extra == 'lint'
Provides-Extra: test
Requires-Dist: pytest ; extra == 'test'
Requires-Dist: pytest-code ; extra == 'test'
Provides-Extra: testing
Requires-Dist: tox ; extra == 'testing'
Requires-Dist: setuptools ; extra == 'testing'
Requires-Dist: pytest ; extra == 'testing'
Requires-Dist: pytest-cov ; extra == 'testing'
